{
  "buy_signals": [
    {
      "symbol": "VET",
      "name": "VeChain",
      "price": 0.04750246913330602,
      "rsi": 0.0,
      "volume": 77503187.7578961,
      "percent_change_24h": -0.08851288,
      "buy": 50.04,
      "sell": 49.96,
      "coin_id": {
        "id": 3077,
        "icon_url": "https://s2.coinmarketcap.com/static/img/coins/64x64/3077.png"
      }
    }
  ],
  "top_10_cryptos": [
    {
      "rank": 1,
      "name": "Bitcoin",
      "symbol": "BTC",
      "market_cap": 1904783056087.8796,
      "price": 96192.43911450656,
      "volume": 47420210028.50346
    },
    {
      "rank": 2,
      "name": "Ethereum",
      "symbol": "ETH",
      "market_cap": 408324545128.07587,
      "price": 3389.5843485963883,
      "volume": 23891701952.159523
    },
    {
      "rank": 3,
      "name": "Tether USDt",
      "symbol": "USDT",
      "market_cap": 139249606914.786,
      "price": 0.9986304245830415,
      "volume": 103059211798.53558
    },
    {
      "rank": 4,
      "name": "XRP",
      "symbol": "XRP",
      "market_cap": 125135944174.50511,
      "price": 2.1796803571164696,
      "volume": 5610351852.564676
    },
    {
      "rank": 5,
      "name": "BNB",
      "symbol": "BNB",
      "market_cap": 100881361471.76196,
      "price": 700.5293743399443,
      "volume": 1211211455.3282764
    },
    {
      "rank": 6,
      "name": "Solana",
      "symbol": "SOL",
      "market_cap": 90921256106.08916,
      "price": 189.60292691246534,
      "volume": 2757838760.943422
    },
    {
      "rank": 7,
      "name": "Dogecoin",
      "symbol": "DOGE",
      "market_cap": 46790504914.087006,
      "price": 0.3174972265078381,
      "volume": 2306793456.094225
    },
    {
      "rank": 8,
      "name": "USDC",
      "symbol": "USDC",
      "market_cap": 43557256388.248535,
      "price": 0.9998857430417465,
      "volume": 6548621892.227214
    },
    {
      "rank": 9,
      "name": "Cardano",
      "symbol": "ADA",
      "market_cap": 31336694066.090473,
      "price": 0.8919728707174429,
      "volume": 837452443.9685131
    },
    {
      "rank": 10,
      "name": "TRON",
      "symbol": "TRX",
      "market_cap": 22221230595.21751,
      "price": 0.2577692523271889,
      "volume": 1056837846.7138017
    }
  ],
  "best_bet": {
    "symbol": "VET",
    "name": "VeChain",
    "price": 0.04750246913330602,
    "rsi": 0.0,
    "volume": 77503187.7578961,
    "percent_change_24h": -0.08851288,
    "buy": 50.04,
    "sell": 49.96,
    "coin_id": {
      "id": 3077,
      "icon_url": "https://s2.coinmarketcap.com/static/img/coins/64x64/3077.png"
    }
  },
  "suggested_holding_time": 14,
  "projected_profit_per_100": -1.23,
  "timestamp": "2024-12-27 10:43:44 UTC"
}