{
  "buy_signals": [],
  "top_10_cryptos": [
    {
      "rank": 1,
      "name": "Bitcoin",
      "symbol": "BTC",
      "market_cap": 1878419006888.7034,
      "price": 94848.49751374648,
      "volume": 27458373181.163033
    },
    {
      "rank": 2,
      "name": "Ethereum",
      "symbol": "ETH",
      "market_cap": 407504258972.8355,
      "price": 3382.4740126887536,
      "volume": 16212065147.362183
    },
    {
      "rank": 3,
      "name": "XRP",
      "symbol": "XRP",
      "market_cap": 138568387741.5845,
      "price": 2.413653366105869,
      "volume": 9877585778.345314
    },
    {
      "rank": 4,
      "name": "Tether USDt",
      "symbol": "USDT",
      "market_cap": 137189653336.01001,
      "price": 0.9982317826263875,
      "volume": 77465139063.84338
    },
    {
      "rank": 5,
      "name": "BNB",
      "symbol": "BNB",
      "market_cap": 100940182140.14793,
      "price": 700.9396087260163,
      "volume": 1595679671.1516402
    },
    {
      "rank": 6,
      "name": "Solana",
      "symbol": "SOL",
      "market_cap": 95852202537.86641,
      "price": 198.5259802043781,
      "volume": 2854060856.292143
    },
    {
      "rank": 7,
      "name": "Dogecoin",
      "symbol": "DOGE",
      "market_cap": 48891286250.79978,
      "price": 0.331576686329789,
      "volume": 2259475492.190731
    },
    {
      "rank": 8,
      "name": "USDC",
      "symbol": "USDC",
      "market_cap": 43712088727.656525,
      "price": 1.00007004357618,
      "volume": 6091310566.555687
    },
    {
      "rank": 9,
      "name": "Cardano",
      "symbol": "ADA",
      "market_cap": 33021573977.01312,
      "price": 0.9397205326809233,
      "volume": 1189002496.8335526
    },
    {
      "rank": 10,
      "name": "TRON",
      "symbol": "TRX",
      "market_cap": 22177843495.89912,
      "price": 0.2572917068223707,
      "volume": 516120197.9529955
    }
  ],
  "best_bet": null,
  "suggested_holding_time": null,
  "projected_profit_per_100": null,
  "timestamp": "2025-01-02 04:09:25 UTC"
}