{
  "buy_signals": [
    {
      "symbol": "AVAX",
      "name": "Avalanche",
      "price": 36.45762321169641,
      "rsi": 0.0,
      "volume": 474007881.3955505,
      "percent_change_24h": -3.0039372,
      "buy": 50.01,
      "sell": 49.99,
      "coin_id": {
        "id": 5805,
        "icon_url": "https://s2.coinmarketcap.com/static/img/coins/64x64/5805.png"
      }
    },
    {
      "symbol": "SHIB",
      "name": "Shiba Inu",
      "price": 2.1405432032963626e-05,
      "rsi": 0.0,
      "volume": 498008645.28391945,
      "percent_change_24h": -0.87845007,
      "buy": 50.01,
      "sell": 49.99,
      "coin_id": {
        "id": 33894,
        "icon_url": "https://s2.coinmarketcap.com/static/img/coins/64x64/33894.png"
      }
    },
    {
      "symbol": "XLM",
      "name": "Stellar",
      "price": 0.3459355743523212,
      "rsi": 0.0,
      "volume": 297288971.5021368,
      "percent_change_24h": -3.25867326,
      "buy": 50.01,
      "sell": 49.99,
      "coin_id": {
        "id": 512,
        "icon_url": "https://s2.coinmarketcap.com/static/img/coins/64x64/512.png"
      }
    },
    {
      "symbol": "DOT",
      "name": "Polkadot",
      "price": 6.832311728551577,
      "rsi": 0.0,
      "volume": 299041148.4826613,
      "percent_change_24h": -2.23484406,
      "buy": 50.01,
      "sell": 49.99,
      "coin_id": {
        "id": 6636,
        "icon_url": "https://s2.coinmarketcap.com/static/img/coins/64x64/6636.png"
      }
    },
    {
      "symbol": "LTC",
      "name": "Litecoin",
      "price": 100.68103209952633,
      "rsi": 0.0,
      "volume": 528785339.2527472,
      "percent_change_24h": -2.10877249,
      "buy": 50.01,
      "sell": 49.99,
      "coin_id": {
        "id": 2,
        "icon_url": "https://s2.coinmarketcap.com/static/img/coins/64x64/2.png"
      }
    },
    {
      "symbol": "NEAR",
      "name": "NEAR Protocol",
      "price": 5.0453166849252415,
      "rsi": 0.0,
      "volume": 284843855.2208929,
      "percent_change_24h": -0.58060859,
      "buy": 50.01,
      "sell": 49.99,
      "coin_id": {
        "id": 6535,
        "icon_url": "https://s2.coinmarketcap.com/static/img/coins/64x64/6535.png"
      }
    },
    {
      "symbol": "AAVE",
      "name": "Aave",
      "price": 322.82768407372646,
      "rsi": 0.0,
      "volume": 662145037.6420124,
      "percent_change_24h": -4.39541374,
      "buy": 50.01,
      "sell": 49.99,
      "coin_id": {
        "id": 7278,
        "icon_url": "https://s2.coinmarketcap.com/static/img/coins/64x64/7278.png"
      }
    },
    {
      "symbol": "APT",
      "name": "Aptos",
      "price": 8.683462605846898,
      "rsi": 0.0,
      "volume": 324389467.7434927,
      "percent_change_24h": -3.29003715,
      "buy": 50.01,
      "sell": 49.99,
      "coin_id": {
        "id": 21794,
        "icon_url": "https://s2.coinmarketcap.com/static/img/coins/64x64/21794.png"
      }
    },
    {
      "symbol": "ICP",
      "name": "Internet Computer",
      "price": 10.109894762853887,
      "rsi": 0.0,
      "volume": 171715059.80516273,
      "percent_change_24h": -2.45762321,
      "buy": 50.02,
      "sell": 49.98,
      "coin_id": {
        "id": 8916,
        "icon_url": "https://s2.coinmarketcap.com/static/img/coins/64x64/8916.png"
      }
    },
    {
      "symbol": "POL",
      "name": "POL (ex-MATIC)",
      "price": 0.47678027295747866,
      "rsi": 0.0,
      "volume": 203995083.51861385,
      "percent_change_24h": -1.04063811,
      "buy": 50.02,
      "sell": 49.98,
      "coin_id": {
        "id": 28321,
        "icon_url": "https://s2.coinmarketcap.com/static/img/coins/64x64/28321.png"
      }
    },
    {
      "symbol": "CRO",
      "name": "Cronos",
      "price": 0.14997166850987653,
      "rsi": 0.0,
      "volume": 29322353.78848626,
      "percent_change_24h": -0.54236006,
      "buy": 50.1,
      "sell": 49.9,
      "coin_id": {
        "id": 3635,
        "icon_url": "https://s2.coinmarketcap.com/static/img/coins/64x64/3635.png"
      }
    },
    {
      "symbol": "VET",
      "name": "VeChain",
      "price": 0.045745889240770894,
      "rsi": 0.0,
      "volume": 79571358.86121579,
      "percent_change_24h": -3.38567064,
      "buy": 50.04,
      "sell": 49.96,
      "coin_id": {
        "id": 3077,
        "icon_url": "https://s2.coinmarketcap.com/static/img/coins/64x64/3077.png"
      }
    },
    {
      "symbol": "RENDER",
      "name": "Render",
      "price": 6.975865335412103,
      "rsi": 0.0,
      "volume": 368394027.3035026,
      "percent_change_24h": -2.98076904,
      "buy": 50.01,
      "sell": 49.99,
      "coin_id": {
        "id": 5690,
        "icon_url": "https://s2.coinmarketcap.com/static/img/coins/64x64/5690.png"
      }
    },
    {
      "symbol": "FIL",
      "name": "Filecoin",
      "price": 4.905300950927981,
      "rsi": 0.0,
      "volume": 225274945.58304912,
      "percent_change_24h": -1.86309104,
      "buy": 50.01,
      "sell": 49.99,
      "coin_id": {
        "id": 2280,
        "icon_url": "https://s2.coinmarketcap.com/static/img/coins/64x64/2280.png"
      }
    },
    {
      "symbol": "ALGO",
      "name": "Algorand",
      "price": 0.3329385520548922,
      "rsi": 0.0,
      "volume": 239328776.4541311,
      "percent_change_24h": -5.34292123,
      "buy": 50.02,
      "sell": 49.98,
      "coin_id": {
        "id": 4030,
        "icon_url": "https://s2.coinmarketcap.com/static/img/coins/64x64/4030.png"
      }
    },
    {
      "symbol": "ATOM",
      "name": "Cosmos",
      "price": 6.433209429608539,
      "rsi": 0.0,
      "volume": 154701014.7298176,
      "percent_change_24h": -1.37881023,
      "buy": 50.02,
      "sell": 49.98,
      "coin_id": {
        "id": 30019,
        "icon_url": "https://s2.coinmarketcap.com/static/img/coins/64x64/30019.png"
      }
    }
  ],
  "top_10_cryptos": [
    {
      "rank": 1,
      "name": "Bitcoin",
      "symbol": "BTC",
      "market_cap": 1865600923662.1194,
      "price": 94213.21393515155,
      "volume": 49556978767.985054
    },
    {
      "rank": 2,
      "name": "Ethereum",
      "symbol": "ETH",
      "market_cap": 399086675531.4509,
      "price": 3312.898931144266,
      "volume": 24908979677.35094
    },
    {
      "rank": 3,
      "name": "Tether USDt",
      "symbol": "USDT",
      "market_cap": 139229406156.4996,
      "price": 0.9984855545739161,
      "volume": 106592364243.79295
    },
    {
      "rank": 4,
      "name": "XRP",
      "symbol": "XRP",
      "market_cap": 122048938262.73512,
      "price": 2.1259093467758743,
      "volume": 5628331422.738523
    },
    {
      "rank": 5,
      "name": "BNB",
      "symbol": "BNB",
      "market_cap": 98818415972.78424,
      "price": 686.2042134508498,
      "volume": 1888880619.849182
    },
    {
      "rank": 6,
      "name": "Solana",
      "symbol": "SOL",
      "market_cap": 87921878095.44987,
      "price": 183.3487157171194,
      "volume": 2843716291.7299156
    },
    {
      "rank": 7,
      "name": "Dogecoin",
      "symbol": "DOGE",
      "market_cap": 45732867941.11217,
      "price": 0.31031352906737036,
      "volume": 2323111198.735004
    },
    {
      "rank": 8,
      "name": "USDC",
      "symbol": "USDC",
      "market_cap": 43560027840.7937,
      "price": 0.9999978720742215,
      "volume": 6717012916.178342
    },
    {
      "rank": 9,
      "name": "Cardano",
      "symbol": "ADA",
      "market_cap": 30496705036.279255,
      "price": 0.8680632832953723,
      "volume": 904888509.4966526
    },
    {
      "rank": 10,
      "name": "TRON",
      "symbol": "TRX",
      "market_cap": 22218708976.66532,
      "price": 0.2577453160740977,
      "volume": 1300097324.4666815
    }
  ],
  "best_bet": {
    "symbol": "CRO",
    "name": "Cronos",
    "price": 0.14997166850987653,
    "rsi": 0.0,
    "volume": 29322353.78848626,
    "percent_change_24h": -0.54236006,
    "buy": 50.1,
    "sell": 49.9,
    "coin_id": {
      "id": 3635,
      "icon_url": "https://s2.coinmarketcap.com/static/img/coins/64x64/3635.png"
    }
  },
  "suggested_holding_time": 14,
  "projected_profit_per_100": -7.33,
  "timestamp": "2024-12-27 16:29:55 UTC"
}