{
  "buy_signals": [],
  "top_10_cryptos": [
    {
      "rank": 1,
      "name": "Bitcoin",
      "symbol": "BTC",
      "market_cap": 1897748944673.404,
      "price": 95824.38936556994,
      "volume": 28228378244.71809
    },
    {
      "rank": 2,
      "name": "Ethereum",
      "symbol": "ETH",
      "market_cap": 411834492522.26807,
      "price": 3418.4169559275506,
      "volume": 16556759572.212074
    },
    {
      "rank": 3,
      "name": "XRP",
      "symbol": "XRP",
      "market_cap": 138742624134.8862,
      "price": 2.4166883026021715,
      "volume": 10065331831.616049
    },
    {
      "rank": 4,
      "name": "Tether USDt",
      "symbol": "USDT",
      "market_cap": 137187167799.01567,
      "price": 0.9982136971369624,
      "volume": 79259243789.71515
    },
    {
      "rank": 5,
      "name": "BNB",
      "symbol": "BNB",
      "market_cap": 101729185911.94695,
      "price": 706.4185483507756,
      "volume": 1619441325.2350464
    },
    {
      "rank": 6,
      "name": "Solana",
      "symbol": "SOL",
      "market_cap": 98611296463.66965,
      "price": 204.2406843597333,
      "volume": 3052451093.5538254
    },
    {
      "rank": 7,
      "name": "Dogecoin",
      "symbol": "DOGE",
      "market_cap": 49354302045.289,
      "price": 0.334715754498617,
      "volume": 2294534454.9819098
    },
    {
      "rank": 8,
      "name": "USDC",
      "symbol": "USDC",
      "market_cap": 43724491853.539665,
      "price": 1.0001467639888197,
      "volume": 6034059245.393593
    },
    {
      "rank": 9,
      "name": "Cardano",
      "symbol": "ADA",
      "market_cap": 33186854585.033756,
      "price": 0.9444240510873778,
      "volume": 1198975440.2242858
    },
    {
      "rank": 10,
      "name": "TRON",
      "symbol": "TRX",
      "market_cap": 22278911794.69975,
      "price": 0.25846415943546547,
      "volume": 525001093.94084036
    }
  ],
  "best_bet": null,
  "suggested_holding_time": null,
  "projected_profit_per_100": null,
  "timestamp": "2025-01-02 04:50:58 UTC"
}