{
  "buy_signals": [
    {
      "symbol": "AVAX",
      "name": "Avalanche",
      "price": 36.85673775225665,
      "rsi": 0.0,
      "volume": 467711774.9754257,
      "percent_change_24h": -1.1155772,
      "buy": 50.01,
      "sell": 49.99,
      "coin_id": {
        "id": 5805,
        "icon_url": "https://s2.coinmarketcap.com/static/img/coins/64x64/5805.png"
      }
    },
    {
      "symbol": "LINK",
      "name": "Chainlink",
      "price": 21.23577732962744,
      "rsi": 0.0,
      "volume": 508487689.570554,
      "percent_change_24h": -1.79013787,
      "buy": 50.01,
      "sell": 49.99,
      "coin_id": {
        "id": 1975,
        "icon_url": "https://s2.coinmarketcap.com/static/img/coins/64x64/1975.png"
      }
    },
    {
      "symbol": "SHIB",
      "name": "Shiba Inu",
      "price": 2.164193305733935e-05,
      "rsi": 0.0,
      "volume": 402581051.53404236,
      "percent_change_24h": -2.64786398,
      "buy": 50.01,
      "sell": 49.99,
      "coin_id": {
        "id": 33894,
        "icon_url": "https://s2.coinmarketcap.com/static/img/coins/64x64/33894.png"
      }
    },
    {
      "symbol": "HBAR",
      "name": "Hedera",
      "price": 0.2809136754647141,
      "rsi": 0.0,
      "volume": 536877309.9959977,
      "percent_change_24h": -3.62024544,
      "buy": 50.01,
      "sell": 49.99,
      "coin_id": {
        "id": 4642,
        "icon_url": "https://s2.coinmarketcap.com/static/img/coins/64x64/4642.png"
      }
    },
    {
      "symbol": "DOT",
      "name": "Polkadot",
      "price": 6.939694634956814,
      "rsi": 0.0,
      "volume": 231188325.30338368,
      "percent_change_24h": -1.8214354,
      "buy": 50.01,
      "sell": 49.99,
      "coin_id": {
        "id": 6636,
        "icon_url": "https://s2.coinmarketcap.com/static/img/coins/64x64/6636.png"
      }
    },
    {
      "symbol": "XLM",
      "name": "Stellar",
      "price": 0.336438552722907,
      "rsi": 0.0,
      "volume": 211204273.39322776,
      "percent_change_24h": -4.5534673,
      "buy": 50.02,
      "sell": 49.98,
      "coin_id": {
        "id": 512,
        "icon_url": "https://s2.coinmarketcap.com/static/img/coins/64x64/512.png"
      }
    },
    {
      "symbol": "BCH",
      "name": "Bitcoin Cash",
      "price": 447.00617764651673,
      "rsi": 0.0,
      "volume": 250295140.50459144,
      "percent_change_24h": -0.94569272,
      "buy": 50.01,
      "sell": 49.99,
      "coin_id": {
        "id": 1831,
        "icon_url": "https://s2.coinmarketcap.com/static/img/coins/64x64/1831.png"
      }
    },
    {
      "symbol": "NEAR",
      "name": "NEAR Protocol",
      "price": 5.193285113844234,
      "rsi": 0.0,
      "volume": 215578890.72638428,
      "percent_change_24h": -2.32813629,
      "buy": 50.02,
      "sell": 49.98,
      "coin_id": {
        "id": 6535,
        "icon_url": "https://s2.coinmarketcap.com/static/img/coins/64x64/6535.png"
      }
    },
    {
      "symbol": "AAVE",
      "name": "Aave",
      "price": 335.09236111069856,
      "rsi": 0.0,
      "volume": 474050750.63616586,
      "percent_change_24h": -0.71201269,
      "buy": 50.01,
      "sell": 49.99,
      "coin_id": {
        "id": 7278,
        "icon_url": "https://s2.coinmarketcap.com/static/img/coins/64x64/7278.png"
      }
    },
    {
      "symbol": "ICP",
      "name": "Internet Computer",
      "price": 10.329863107548634,
      "rsi": 0.0,
      "volume": 135605650.95076415,
      "percent_change_24h": -1.97789396,
      "buy": 50.02,
      "sell": 49.98,
      "coin_id": {
        "id": 8916,
        "icon_url": "https://s2.coinmarketcap.com/static/img/coins/64x64/8916.png"
      }
    },
    {
      "symbol": "POL",
      "name": "POL (ex-MATIC)",
      "price": 0.47256287383090867,
      "rsi": 0.0,
      "volume": 157535408.41336298,
      "percent_change_24h": -2.62009709,
      "buy": 50.02,
      "sell": 49.98,
      "coin_id": {
        "id": 28321,
        "icon_url": "https://s2.coinmarketcap.com/static/img/coins/64x64/28321.png"
      }
    },
    {
      "symbol": "ETC",
      "name": "Ethereum Classic",
      "price": 25.89884145544071,
      "rsi": 0.0,
      "volume": 168989171.5838709,
      "percent_change_24h": -2.03974261,
      "buy": 50.02,
      "sell": 49.98,
      "coin_id": {
        "id": 1321,
        "icon_url": "https://s2.coinmarketcap.com/static/img/coins/64x64/1321.png"
      }
    },
    {
      "symbol": "VET",
      "name": "VeChain",
      "price": 0.045275292174300596,
      "rsi": 0.0,
      "volume": 53275498.85870279,
      "percent_change_24h": -2.85999772,
      "buy": 50.06,
      "sell": 49.94,
      "coin_id": {
        "id": 3077,
        "icon_url": "https://s2.coinmarketcap.com/static/img/coins/64x64/3077.png"
      }
    },
    {
      "symbol": "RENDER",
      "name": "Render",
      "price": 6.929266235823758,
      "rsi": 0.0,
      "volume": 282857422.98775697,
      "percent_change_24h": -2.36125131,
      "buy": 50.01,
      "sell": 49.99,
      "coin_id": {
        "id": 5690,
        "icon_url": "https://s2.coinmarketcap.com/static/img/coins/64x64/5690.png"
      }
    },
    {
      "symbol": "FET",
      "name": "Artificial Superintelligence Alliance",
      "price": 1.3295066931112287,
      "rsi": 0.0,
      "volume": 198242877.22602692,
      "percent_change_24h": -1.1175562,
      "buy": 50.02,
      "sell": 49.98,
      "coin_id": {
        "id": 3773,
        "icon_url": "https://s2.coinmarketcap.com/static/img/coins/64x64/3773.png"
      }
    },
    {
      "symbol": "ARB",
      "name": "Arbitrum",
      "price": 0.7617214801298842,
      "rsi": 0.0,
      "volume": 252453666.53888595,
      "percent_change_24h": -1.53379824,
      "buy": 50.01,
      "sell": 49.99,
      "coin_id": {
        "id": 21129,
        "icon_url": "https://s2.coinmarketcap.com/static/img/coins/64x64/21129.png"
      }
    },
    {
      "symbol": "FIL",
      "name": "Filecoin",
      "price": 5.030274339347184,
      "rsi": 0.0,
      "volume": 193448229.68002328,
      "percent_change_24h": -2.24046377,
      "buy": 50.02,
      "sell": 49.98,
      "coin_id": {
        "id": 2280,
        "icon_url": "https://s2.coinmarketcap.com/static/img/coins/64x64/2280.png"
      }
    },
    {
      "symbol": "ALGO",
      "name": "Algorand",
      "price": 0.33069908548243837,
      "rsi": 0.0,
      "volume": 160588643.48392025,
      "percent_change_24h": -2.10607211,
      "buy": 50.02,
      "sell": 49.98,
      "coin_id": {
        "id": 4030,
        "icon_url": "https://s2.coinmarketcap.com/static/img/coins/64x64/4030.png"
      }
    },
    {
      "symbol": "ATOM",
      "name": "Cosmos",
      "price": 6.434147147963865,
      "rsi": 0.0,
      "volume": 129603921.60902715,
      "percent_change_24h": -2.41697721,
      "buy": 50.03,
      "sell": 49.97,
      "coin_id": {
        "id": 30019,
        "icon_url": "https://s2.coinmarketcap.com/static/img/coins/64x64/30019.png"
      }
    }
  ],
  "top_10_cryptos": [
    {
      "rank": 1,
      "name": "Bitcoin",
      "symbol": "BTC",
      "market_cap": 1856171316153.9368,
      "price": 93731.07170194092,
      "volume": 36316844857.48813
    },
    {
      "rank": 2,
      "name": "Ethereum",
      "symbol": "ETH",
      "market_cap": 411295466241.188,
      "price": 3414.0689101624243,
      "volume": 17718112535.11697
    },
    {
      "rank": 3,
      "name": "Tether USDt",
      "symbol": "USDT",
      "market_cap": 138723410987.78394,
      "price": 0.998347170256222,
      "volume": 83121604195.8134
    },
    {
      "rank": 4,
      "name": "XRP",
      "symbol": "XRP",
      "market_cap": 118260387447.10905,
      "price": 2.0599184770123316,
      "volume": 4437737749.787895
    },
    {
      "rank": 5,
      "name": "BNB",
      "symbol": "BNB",
      "market_cap": 100229741094.42601,
      "price": 696.0053690784903,
      "volume": 1681601471.2274046
    },
    {
      "rank": 6,
      "name": "Solana",
      "symbol": "SOL",
      "market_cap": 92576607422.51328,
      "price": 192.97383485862093,
      "volume": 2342833997.0973296
    },
    {
      "rank": 7,
      "name": "Dogecoin",
      "symbol": "DOGE",
      "market_cap": 47229553240.79388,
      "price": 0.32038940942181976,
      "volume": 1942876389.4319947
    },
    {
      "rank": 8,
      "name": "USDC",
      "symbol": "USDC",
      "market_cap": 43618987786.237305,
      "price": 1.0002848171450156,
      "volume": 5604078876.085408
    },
    {
      "rank": 9,
      "name": "Cardano",
      "symbol": "ADA",
      "market_cap": 30528937297.783554,
      "price": 0.8689807477465703,
      "volume": 808899622.3887423
    },
    {
      "rank": 10,
      "name": "TRON",
      "symbol": "TRX",
      "market_cap": 22217379044.439693,
      "price": 0.25773690024825735,
      "volume": 768785113.4466643
    }
  ],
  "best_bet": {
    "symbol": "VET",
    "name": "VeChain",
    "price": 0.045275292174300596,
    "rsi": 0.0,
    "volume": 53275498.85870279,
    "percent_change_24h": -2.85999772,
    "buy": 50.06,
    "sell": 49.94,
    "coin_id": {
      "id": 3077,
      "icon_url": "https://s2.coinmarketcap.com/static/img/coins/64x64/3077.png"
    }
  },
  "suggested_holding_time": 7,
  "projected_profit_per_100": -18.38,
  "timestamp": "2024-12-30 08:50:58 UTC"
}