{
  "buy_signals": [
    {
      "symbol": "ADA",
      "name": "Cardano",
      "price": 0.8727709571769325,
      "rsi": 0.0,
      "volume": 712050893.2689357,
      "percent_change_24h": -3.94419395,
      "buy": 50.01,
      "sell": 49.99,
      "coin_id": {
        "id": 2010,
        "icon_url": "https://s2.coinmarketcap.com/static/img/coins/64x64/2010.png"
      }
    },
    {
      "symbol": "AVAX",
      "name": "Avalanche",
      "price": 36.73092924560882,
      "rsi": 0.0,
      "volume": 378719089.32666725,
      "percent_change_24h": -5.26882681,
      "buy": 50.01,
      "sell": 49.99,
      "coin_id": {
        "id": 5805,
        "icon_url": "https://s2.coinmarketcap.com/static/img/coins/64x64/5805.png"
      }
    },
    {
      "symbol": "LINK",
      "name": "Chainlink",
      "price": 21.31735145407367,
      "rsi": 0.0,
      "volume": 744401413.2275237,
      "percent_change_24h": -9.70771219,
      "buy": 50.01,
      "sell": 49.99,
      "coin_id": {
        "id": 1975,
        "icon_url": "https://s2.coinmarketcap.com/static/img/coins/64x64/1975.png"
      }
    },
    {
      "symbol": "SHIB",
      "name": "Shiba Inu",
      "price": 2.176241670087043e-05,
      "rsi": 0.0,
      "volume": 360910148.1451665,
      "percent_change_24h": -2.53828266,
      "buy": 50.01,
      "sell": 49.99,
      "coin_id": {
        "id": 33894,
        "icon_url": "https://s2.coinmarketcap.com/static/img/coins/64x64/33894.png"
      }
    },
    {
      "symbol": "XLM",
      "name": "Stellar",
      "price": 0.34850289516891386,
      "rsi": 0.0,
      "volume": 262433894.72511402,
      "percent_change_24h": -4.98969909,
      "buy": 50.01,
      "sell": 49.99,
      "coin_id": {
        "id": 512,
        "icon_url": "https://s2.coinmarketcap.com/static/img/coins/64x64/512.png"
      }
    },
    {
      "symbol": "DOT",
      "name": "Polkadot",
      "price": 6.871691106982581,
      "rsi": 0.0,
      "volume": 264256881.53634977,
      "percent_change_24h": -5.49189,
      "buy": 50.01,
      "sell": 49.99,
      "coin_id": {
        "id": 6636,
        "icon_url": "https://s2.coinmarketcap.com/static/img/coins/64x64/6636.png"
      }
    },
    {
      "symbol": "HBAR",
      "name": "Hedera",
      "price": 0.2751729404914691,
      "rsi": 0.0,
      "volume": 566558129.756044,
      "percent_change_24h": -5.64161276,
      "buy": 50.01,
      "sell": 49.99,
      "coin_id": {
        "id": 4642,
        "icon_url": "https://s2.coinmarketcap.com/static/img/coins/64x64/4642.png"
      }
    },
    {
      "symbol": "BCH",
      "name": "Bitcoin Cash",
      "price": 441.61594845335,
      "rsi": 0.0,
      "volume": 281258706.2636721,
      "percent_change_24h": -3.9142871,
      "buy": 50.01,
      "sell": 49.99,
      "coin_id": {
        "id": 1831,
        "icon_url": "https://s2.coinmarketcap.com/static/img/coins/64x64/1831.png"
      }
    },
    {
      "symbol": "UNI",
      "name": "Uniswap",
      "price": 13.271197898985479,
      "rsi": 0.0,
      "volume": 308938825.7017337,
      "percent_change_24h": -6.1186045,
      "buy": 50.01,
      "sell": 49.99,
      "coin_id": {
        "id": 33433,
        "icon_url": "https://s2.coinmarketcap.com/static/img/coins/64x64/33433.png"
      }
    },
    {
      "symbol": "LTC",
      "name": "Litecoin",
      "price": 99.73591874261548,
      "rsi": 0.0,
      "volume": 466303358.8839103,
      "percent_change_24h": -5.94637899,
      "buy": 50.01,
      "sell": 49.99,
      "coin_id": {
        "id": 2,
        "icon_url": "https://s2.coinmarketcap.com/static/img/coins/64x64/2.png"
      }
    },
    {
      "symbol": "NEAR",
      "name": "NEAR Protocol",
      "price": 5.170052338684651,
      "rsi": 0.0,
      "volume": 255398576.53522602,
      "percent_change_24h": -2.23693164,
      "buy": 50.01,
      "sell": 49.99,
      "coin_id": {
        "id": 6535,
        "icon_url": "https://s2.coinmarketcap.com/static/img/coins/64x64/6535.png"
      }
    },
    {
      "symbol": "AAVE",
      "name": "Aave",
      "price": 328.28764187353835,
      "rsi": 0.0,
      "volume": 489416079.30452204,
      "percent_change_24h": -5.80761314,
      "buy": 50.01,
      "sell": 49.99,
      "coin_id": {
        "id": 7278,
        "icon_url": "https://s2.coinmarketcap.com/static/img/coins/64x64/7278.png"
      }
    },
    {
      "symbol": "APT",
      "name": "Aptos",
      "price": 8.829319704784162,
      "rsi": 0.0,
      "volume": 279728672.8946589,
      "percent_change_24h": -4.6532142,
      "buy": 50.01,
      "sell": 49.99,
      "coin_id": {
        "id": 21794,
        "icon_url": "https://s2.coinmarketcap.com/static/img/coins/64x64/21794.png"
      }
    },
    {
      "symbol": "ICP",
      "name": "Internet Computer",
      "price": 10.195074426767338,
      "rsi": 0.0,
      "volume": 151357598.15752444,
      "percent_change_24h": -5.32960147,
      "buy": 50.03,
      "sell": 49.97,
      "coin_id": {
        "id": 8916,
        "icon_url": "https://s2.coinmarketcap.com/static/img/coins/64x64/8916.png"
      }
    },
    {
      "symbol": "POL",
      "name": "POL (ex-MATIC)",
      "price": 0.4800393412050579,
      "rsi": 0.0,
      "volume": 176050755.82460886,
      "percent_change_24h": -3.91323908,
      "buy": 50.02,
      "sell": 49.98,
      "coin_id": {
        "id": 28321,
        "icon_url": "https://s2.coinmarketcap.com/static/img/coins/64x64/28321.png"
      }
    },
    {
      "symbol": "CRO",
      "name": "Cronos",
      "price": 0.1479966078867332,
      "rsi": 0.0,
      "volume": 31071581.40342096,
      "percent_change_24h": -4.42376232,
      "buy": 50.12,
      "sell": 49.88,
      "coin_id": {
        "id": 3635,
        "icon_url": "https://s2.coinmarketcap.com/static/img/coins/64x64/3635.png"
      }
    },
    {
      "symbol": "ETC",
      "name": "Ethereum Classic",
      "price": 26.055514289012116,
      "rsi": 0.0,
      "volume": 161432808.82976264,
      "percent_change_24h": -3.44744976,
      "buy": 50.02,
      "sell": 49.98,
      "coin_id": {
        "id": 1321,
        "icon_url": "https://s2.coinmarketcap.com/static/img/coins/64x64/1321.png"
      }
    },
    {
      "symbol": "VET",
      "name": "VeChain",
      "price": 0.045626060749461066,
      "rsi": 0.0,
      "volume": 62006777.31563377,
      "percent_change_24h": -6.04060058,
      "buy": 50.06,
      "sell": 49.94,
      "coin_id": {
        "id": 3077,
        "icon_url": "https://s2.coinmarketcap.com/static/img/coins/64x64/3077.png"
      }
    },
    {
      "symbol": "RENDER",
      "name": "Render",
      "price": 6.948636812187291,
      "rsi": 0.0,
      "volume": 338093615.8097318,
      "percent_change_24h": -7.22705048,
      "buy": 50.01,
      "sell": 49.99,
      "coin_id": {
        "id": 5690,
        "icon_url": "https://s2.coinmarketcap.com/static/img/coins/64x64/5690.png"
      }
    },
    {
      "symbol": "ARB",
      "name": "Arbitrum",
      "price": 0.7571440731390192,
      "rsi": 0.0,
      "volume": 297522277.8511706,
      "percent_change_24h": -4.40593304,
      "buy": 50.01,
      "sell": 49.99,
      "coin_id": {
        "id": 21129,
        "icon_url": "https://s2.coinmarketcap.com/static/img/coins/64x64/21129.png"
      }
    },
    {
      "symbol": "FET",
      "name": "Artificial Superintelligence Alliance",
      "price": 1.3096514737055016,
      "rsi": 0.0,
      "volume": 240990849.46387714,
      "percent_change_24h": -2.74350237,
      "buy": 50.01,
      "sell": 49.99,
      "coin_id": {
        "id": 3773,
        "icon_url": "https://s2.coinmarketcap.com/static/img/coins/64x64/3773.png"
      }
    },
    {
      "symbol": "FIL",
      "name": "Filecoin",
      "price": 4.997204356488229,
      "rsi": 0.0,
      "volume": 204916750.3533456,
      "percent_change_24h": -3.58264193,
      "buy": 50.02,
      "sell": 49.98,
      "coin_id": {
        "id": 2280,
        "icon_url": "https://s2.coinmarketcap.com/static/img/coins/64x64/2280.png"
      }
    },
    {
      "symbol": "ALGO",
      "name": "Algorand",
      "price": 0.33220082603087964,
      "rsi": 0.0,
      "volume": 202130801.02652287,
      "percent_change_24h": -9.75819319,
      "buy": 50.02,
      "sell": 49.98,
      "coin_id": {
        "id": 4030,
        "icon_url": "https://s2.coinmarketcap.com/static/img/coins/64x64/4030.png"
      }
    },
    {
      "symbol": "ATOM",
      "name": "Cosmos",
      "price": 6.4579023423079915,
      "rsi": 0.0,
      "volume": 128993074.9182855,
      "percent_change_24h": -4.76668118,
      "buy": 50.03,
      "sell": 49.97,
      "coin_id": {
        "id": 30019,
        "icon_url": "https://s2.coinmarketcap.com/static/img/coins/64x64/30019.png"
      }
    },
    {
      "symbol": "OP",
      "name": "Optimism",
      "price": 1.8559362637081045,
      "rsi": 0.0,
      "volume": 260405019.3403077,
      "percent_change_24h": -0.92606582,
      "buy": 50.01,
      "sell": 49.99,
      "coin_id": {
        "id": 11840,
        "icon_url": "https://s2.coinmarketcap.com/static/img/coins/64x64/11840.png"
      }
    }
  ],
  "top_10_cryptos": [
    {
      "rank": 1,
      "name": "Bitcoin",
      "symbol": "BTC",
      "market_cap": 1870956262083.4229,
      "price": 94481.9466626299,
      "volume": 40900403020.83433
    },
    {
      "rank": 2,
      "name": "Ethereum",
      "symbol": "ETH",
      "market_cap": 403220076522.6864,
      "price": 3347.1545871507788,
      "volume": 19567143913.05562
    },
    {
      "rank": 3,
      "name": "Tether USDt",
      "symbol": "USDT",
      "market_cap": 138779475222.9845,
      "price": 0.9983770264759617,
      "volume": 89931336432.33516
    },
    {
      "rank": 4,
      "name": "XRP",
      "symbol": "XRP",
      "market_cap": 124408453230.22784,
      "price": 2.167008556606378,
      "volume": 4136278437.5239115
    },
    {
      "rank": 5,
      "name": "BNB",
      "symbol": "BNB",
      "market_cap": 100746417566.93594,
      "price": 699.5926274760989,
      "volume": 1628768326.1404283
    },
    {
      "rank": 6,
      "name": "Solana",
      "symbol": "SOL",
      "market_cap": 89224197618.86963,
      "price": 186.02336218353048,
      "volume": 2316212122.678144
    },
    {
      "rank": 7,
      "name": "Dogecoin",
      "symbol": "DOGE",
      "market_cap": 46717189329.08975,
      "price": 0.3169712664778065,
      "volume": 1746046895.566132
    },
    {
      "rank": 8,
      "name": "USDC",
      "symbol": "USDC",
      "market_cap": 43557913394.91103,
      "price": 1.0000018244765696,
      "volume": 5729769916.673578
    },
    {
      "rank": 9,
      "name": "Cardano",
      "symbol": "ADA",
      "market_cap": 30661557518.959866,
      "price": 0.8727556717748781,
      "volume": 714567717.5257841
    },
    {
      "rank": 10,
      "name": "TRON",
      "symbol": "TRX",
      "market_cap": 22306665577.492184,
      "price": 0.2587668298660064,
      "volume": 1075291477.5402303
    }
  ],
  "best_bet": {
    "symbol": "CRO",
    "name": "Cronos",
    "price": 0.1479966078867332,
    "rsi": 0.0,
    "volume": 31071581.40342096,
    "percent_change_24h": -4.42376232,
    "buy": 50.12,
    "sell": 49.88,
    "coin_id": {
      "id": 3635,
      "icon_url": "https://s2.coinmarketcap.com/static/img/coins/64x64/3635.png"
    }
  },
  "suggested_holding_time": 7,
  "projected_profit_per_100": -27.15,
  "timestamp": "2024-12-28 09:50:59 UTC"
}