{
  "buy_signals": [
    {
      "symbol": "ADA",
      "name": "Cardano",
      "price": 0.8703476774812742,
      "rsi": 0.0,
      "volume": 591313783.039163,
      "percent_change_24h": -2.25327286,
      "buy": 50.01,
      "sell": 49.99,
      "coin_id": {
        "id": 2010,
        "icon_url": "https://s2.coinmarketcap.com/static/img/coins/64x64/2010.png"
      }
    },
    {
      "symbol": "AVAX",
      "name": "Avalanche",
      "price": 36.22066576701386,
      "rsi": 0.0,
      "volume": 313049352.43437123,
      "percent_change_24h": -4.1217278,
      "buy": 50.01,
      "sell": 49.99,
      "coin_id": {
        "id": 5805,
        "icon_url": "https://s2.coinmarketcap.com/static/img/coins/64x64/5805.png"
      }
    },
    {
      "symbol": "LINK",
      "name": "Chainlink",
      "price": 21.25616505682674,
      "rsi": 0.0,
      "volume": 498930052.158052,
      "percent_change_24h": -3.87166967,
      "buy": 50.01,
      "sell": 49.99,
      "coin_id": {
        "id": 1975,
        "icon_url": "https://s2.coinmarketcap.com/static/img/coins/64x64/1975.png"
      }
    },
    {
      "symbol": "SHIB",
      "name": "Shiba Inu",
      "price": 2.1732862921795662e-05,
      "rsi": 0.0,
      "volume": 336526898.81815434,
      "percent_change_24h": -2.45315473,
      "buy": 50.01,
      "sell": 49.99,
      "coin_id": {
        "id": 33894,
        "icon_url": "https://s2.coinmarketcap.com/static/img/coins/64x64/33894.png"
      }
    },
    {
      "symbol": "DOT",
      "name": "Polkadot",
      "price": 6.914907800730408,
      "rsi": 0.0,
      "volume": 202856557.92414668,
      "percent_change_24h": -2.60908289,
      "buy": 50.02,
      "sell": 49.98,
      "coin_id": {
        "id": 6636,
        "icon_url": "https://s2.coinmarketcap.com/static/img/coins/64x64/6636.png"
      }
    },
    {
      "symbol": "XLM",
      "name": "Stellar",
      "price": 0.34484846851730305,
      "rsi": 0.0,
      "volume": 161711646.16343278,
      "percent_change_24h": -3.1734001,
      "buy": 50.02,
      "sell": 49.98,
      "coin_id": {
        "id": 512,
        "icon_url": "https://s2.coinmarketcap.com/static/img/coins/64x64/512.png"
      }
    },
    {
      "symbol": "BCH",
      "name": "Bitcoin Cash",
      "price": 442.18796533711054,
      "rsi": 0.0,
      "volume": 213985326.93874234,
      "percent_change_24h": -1.71103664,
      "buy": 50.02,
      "sell": 49.98,
      "coin_id": {
        "id": 1831,
        "icon_url": "https://s2.coinmarketcap.com/static/img/coins/64x64/1831.png"
      }
    },
    {
      "symbol": "UNI",
      "name": "Uniswap",
      "price": 13.129862222316618,
      "rsi": 0.0,
      "volume": 204539938.38306198,
      "percent_change_24h": -3.02117716,
      "buy": 50.02,
      "sell": 49.98,
      "coin_id": {
        "id": 33433,
        "icon_url": "https://s2.coinmarketcap.com/static/img/coins/64x64/33433.png"
      }
    },
    {
      "symbol": "LTC",
      "name": "Litecoin",
      "price": 99.41134681349928,
      "rsi": 0.0,
      "volume": 377777779.3945614,
      "percent_change_24h": -1.90106458,
      "buy": 50.01,
      "sell": 49.99,
      "coin_id": {
        "id": 2,
        "icon_url": "https://s2.coinmarketcap.com/static/img/coins/64x64/2.png"
      }
    },
    {
      "symbol": "NEAR",
      "name": "NEAR Protocol",
      "price": 5.156134662107336,
      "rsi": 0.0,
      "volume": 217215323.170147,
      "percent_change_24h": -2.16988359,
      "buy": 50.02,
      "sell": 49.98,
      "coin_id": {
        "id": 6535,
        "icon_url": "https://s2.coinmarketcap.com/static/img/coins/64x64/6535.png"
      }
    },
    {
      "symbol": "APT",
      "name": "Aptos",
      "price": 8.968842889325403,
      "rsi": 0.0,
      "volume": 189189107.84336314,
      "percent_change_24h": -1.96849046,
      "buy": 50.02,
      "sell": 49.98,
      "coin_id": {
        "id": 21794,
        "icon_url": "https://s2.coinmarketcap.com/static/img/coins/64x64/21794.png"
      }
    },
    {
      "symbol": "AAVE",
      "name": "Aave",
      "price": 332.3594136705538,
      "rsi": 0.0,
      "volume": 542761823.7577429,
      "percent_change_24h": -1.55996009,
      "buy": 50.01,
      "sell": 49.99,
      "coin_id": {
        "id": 7278,
        "icon_url": "https://s2.coinmarketcap.com/static/img/coins/64x64/7278.png"
      }
    },
    {
      "symbol": "ICP",
      "name": "Internet Computer",
      "price": 10.108591262572162,
      "rsi": 0.0,
      "volume": 118314984.47527969,
      "percent_change_24h": -4.7145639,
      "buy": 50.03,
      "sell": 49.97,
      "coin_id": {
        "id": 8916,
        "icon_url": "https://s2.coinmarketcap.com/static/img/coins/64x64/8916.png"
      }
    },
    {
      "symbol": "POL",
      "name": "POL (ex-MATIC)",
      "price": 0.47274216689897425,
      "rsi": 0.0,
      "volume": 132413703.81618641,
      "percent_change_24h": -3.06743383,
      "buy": 50.03,
      "sell": 49.97,
      "coin_id": {
        "id": 28321,
        "icon_url": "https://s2.coinmarketcap.com/static/img/coins/64x64/28321.png"
      }
    },
    {
      "symbol": "ETC",
      "name": "Ethereum Classic",
      "price": 25.862904948525944,
      "rsi": 0.0,
      "volume": 133871959.88878198,
      "percent_change_24h": -2.76029178,
      "buy": 50.03,
      "sell": 49.97,
      "coin_id": {
        "id": 1321,
        "icon_url": "https://s2.coinmarketcap.com/static/img/coins/64x64/1321.png"
      }
    },
    {
      "symbol": "CRO",
      "name": "Cronos",
      "price": 0.1446293200609459,
      "rsi": 0.0,
      "volume": 21712175.31646558,
      "percent_change_24h": -3.69827822,
      "buy": 50.16,
      "sell": 49.84,
      "coin_id": {
        "id": 3635,
        "icon_url": "https://s2.coinmarketcap.com/static/img/coins/64x64/3635.png"
      }
    },
    {
      "symbol": "VET",
      "name": "VeChain",
      "price": 0.045578399640243,
      "rsi": 0.0,
      "volume": 49586351.30063097,
      "percent_change_24h": -3.24619479,
      "buy": 50.07,
      "sell": 49.93,
      "coin_id": {
        "id": 3077,
        "icon_url": "https://s2.coinmarketcap.com/static/img/coins/64x64/3077.png"
      }
    },
    {
      "symbol": "RENDER",
      "name": "Render",
      "price": 6.950252819182735,
      "rsi": 0.0,
      "volume": 241650746.08770916,
      "percent_change_24h": -3.42882377,
      "buy": 50.01,
      "sell": 49.99,
      "coin_id": {
        "id": 5690,
        "icon_url": "https://s2.coinmarketcap.com/static/img/coins/64x64/5690.png"
      }
    },
    {
      "symbol": "ARB",
      "name": "Arbitrum",
      "price": 0.7536522813904083,
      "rsi": 0.0,
      "volume": 194246240.66044664,
      "percent_change_24h": -2.92072292,
      "buy": 50.02,
      "sell": 49.98,
      "coin_id": {
        "id": 21129,
        "icon_url": "https://s2.coinmarketcap.com/static/img/coins/64x64/21129.png"
      }
    },
    {
      "symbol": "FET",
      "name": "Artificial Superintelligence Alliance",
      "price": 1.2997341246870413,
      "rsi": 0.0,
      "volume": 175516593.8158643,
      "percent_change_24h": -4.49363326,
      "buy": 50.02,
      "sell": 49.98,
      "coin_id": {
        "id": 3773,
        "icon_url": "https://s2.coinmarketcap.com/static/img/coins/64x64/3773.png"
      }
    },
    {
      "symbol": "FIL",
      "name": "Filecoin",
      "price": 5.007097628619074,
      "rsi": 0.0,
      "volume": 181871986.28389376,
      "percent_change_24h": -4.2623859,
      "buy": 50.02,
      "sell": 49.98,
      "coin_id": {
        "id": 2280,
        "icon_url": "https://s2.coinmarketcap.com/static/img/coins/64x64/2280.png"
      }
    },
    {
      "symbol": "ALGO",
      "name": "Algorand",
      "price": 0.32819333655355304,
      "rsi": 0.0,
      "volume": 156619729.10960978,
      "percent_change_24h": -4.38829169,
      "buy": 50.02,
      "sell": 49.98,
      "coin_id": {
        "id": 4030,
        "icon_url": "https://s2.coinmarketcap.com/static/img/coins/64x64/4030.png"
      }
    },
    {
      "symbol": "ATOM",
      "name": "Cosmos",
      "price": 6.391946645240752,
      "rsi": 0.0,
      "volume": 115995708.35867809,
      "percent_change_24h": -3.1791822,
      "buy": 50.03,
      "sell": 49.97,
      "coin_id": {
        "id": 30019,
        "icon_url": "https://s2.coinmarketcap.com/static/img/coins/64x64/30019.png"
      }
    },
    {
      "symbol": "OP",
      "name": "Optimism",
      "price": 1.8243107163525796,
      "rsi": 0.0,
      "volume": 163994723.69245496,
      "percent_change_24h": -3.29182824,
      "buy": 50.02,
      "sell": 49.98,
      "coin_id": {
        "id": 11840,
        "icon_url": "https://s2.coinmarketcap.com/static/img/coins/64x64/11840.png"
      }
    }
  ],
  "top_10_cryptos": [
    {
      "rank": 1,
      "name": "Bitcoin",
      "symbol": "BTC",
      "market_cap": 1855530723647.156,
      "price": 93699.9065969124,
      "volume": 24269023569.53312
    },
    {
      "rank": 2,
      "name": "Ethereum",
      "symbol": "ETH",
      "market_cap": 403294488778.06525,
      "price": 3347.7112415269453,
      "volume": 12674355941.846571
    },
    {
      "rank": 3,
      "name": "Tether USDt",
      "symbol": "USDT",
      "market_cap": 138755843232.56436,
      "price": 0.9982070184770601,
      "volume": 63529356190.203064
    },
    {
      "rank": 4,
      "name": "XRP",
      "symbol": "XRP",
      "market_cap": 123006707519.45732,
      "price": 2.142592249912132,
      "volume": 2461826153.405564
    },
    {
      "rank": 5,
      "name": "BNB",
      "symbol": "BNB",
      "market_cap": 101281843798.67577,
      "price": 703.3111018040623,
      "volume": 1619999925.2830768
    },
    {
      "rank": 6,
      "name": "Solana",
      "symbol": "SOL",
      "market_cap": 92379118123.54663,
      "price": 192.60494568155286,
      "volume": 2242127397.6840944
    },
    {
      "rank": 7,
      "name": "Dogecoin",
      "symbol": "DOGE",
      "market_cap": 46597319085.00019,
      "price": 0.31611930939413263,
      "volume": 1532015816.1679559
    },
    {
      "rank": 8,
      "name": "USDC",
      "symbol": "USDC",
      "market_cap": 43616181103.79852,
      "price": 1.0000512745858021,
      "volume": 4139699490.3753676
    },
    {
      "rank": 9,
      "name": "Cardano",
      "symbol": "ADA",
      "market_cap": 30576960124.83636,
      "price": 0.8703476774812742,
      "volume": 591313783.039163
    },
    {
      "rank": 10,
      "name": "TRON",
      "symbol": "TRX",
      "market_cap": 22330743915.375957,
      "price": 0.2590512794897568,
      "volume": 657227175.3608294
    }
  ],
  "best_bet": {
    "symbol": "CRO",
    "name": "Cronos",
    "price": 0.1446293200609459,
    "rsi": 0.0,
    "volume": 21712175.31646558,
    "percent_change_24h": -3.69827822,
    "buy": 50.16,
    "sell": 49.84,
    "coin_id": {
      "id": 3635,
      "icon_url": "https://s2.coinmarketcap.com/static/img/coins/64x64/3635.png"
    }
  },
  "suggested_holding_time": 7,
  "projected_profit_per_100": -23.19,
  "timestamp": "2024-12-29 17:31:28 UTC"
}