{
  "buy_signals": [
    {
      "symbol": "AVAX",
      "name": "Avalanche",
      "price": 36.5864701249287,
      "rsi": 0.0,
      "volume": 476590500.34443396,
      "percent_change_24h": -2.86842325,
      "buy": 50.01,
      "sell": 49.99,
      "coin_id": {
        "id": 5805,
        "icon_url": "https://s2.coinmarketcap.com/static/img/coins/64x64/5805.png"
      }
    },
    {
      "symbol": "SHIB",
      "name": "Shiba Inu",
      "price": 2.1471454770095268e-05,
      "rsi": 0.0,
      "volume": 488489274.9267036,
      "percent_change_24h": -1.25204062,
      "buy": 50.01,
      "sell": 49.99,
      "coin_id": {
        "id": 33894,
        "icon_url": "https://s2.coinmarketcap.com/static/img/coins/64x64/33894.png"
      }
    },
    {
      "symbol": "DOT",
      "name": "Polkadot",
      "price": 6.860865505656011,
      "rsi": 0.0,
      "volume": 301872695.45660436,
      "percent_change_24h": -2.22188513,
      "buy": 50.01,
      "sell": 49.99,
      "coin_id": {
        "id": 6636,
        "icon_url": "https://s2.coinmarketcap.com/static/img/coins/64x64/6636.png"
      }
    },
    {
      "symbol": "XLM",
      "name": "Stellar",
      "price": 0.34544370150265374,
      "rsi": 0.0,
      "volume": 301078377.8739732,
      "percent_change_24h": -3.1391279,
      "buy": 50.01,
      "sell": 49.99,
      "coin_id": {
        "id": 512,
        "icon_url": "https://s2.coinmarketcap.com/static/img/coins/64x64/512.png"
      }
    },
    {
      "symbol": "LTC",
      "name": "Litecoin",
      "price": 100.91672991231871,
      "rsi": 0.0,
      "volume": 527247922.98953426,
      "percent_change_24h": -2.291318,
      "buy": 50.01,
      "sell": 49.99,
      "coin_id": {
        "id": 2,
        "icon_url": "https://s2.coinmarketcap.com/static/img/coins/64x64/2.png"
      }
    },
    {
      "symbol": "NEAR",
      "name": "NEAR Protocol",
      "price": 5.0754962836622495,
      "rsi": 0.0,
      "volume": 286536719.9386386,
      "percent_change_24h": -0.21208093,
      "buy": 50.01,
      "sell": 49.99,
      "coin_id": {
        "id": 6535,
        "icon_url": "https://s2.coinmarketcap.com/static/img/coins/64x64/6535.png"
      }
    },
    {
      "symbol": "DAI",
      "name": "Dai",
      "price": 0.9995624674662633,
      "rsi": 0.0,
      "volume": 98996650.43526936,
      "percent_change_24h": -0.02559641,
      "buy": 50.03,
      "sell": 49.97,
      "coin_id": {
        "id": 4943,
        "icon_url": "https://s2.coinmarketcap.com/static/img/coins/64x64/4943.png"
      }
    },
    {
      "symbol": "APT",
      "name": "Aptos",
      "price": 8.736594268699235,
      "rsi": 0.0,
      "volume": 325250905.1429434,
      "percent_change_24h": -3.76681761,
      "buy": 50.01,
      "sell": 49.99,
      "coin_id": {
        "id": 21794,
        "icon_url": "https://s2.coinmarketcap.com/static/img/coins/64x64/21794.png"
      }
    },
    {
      "symbol": "AAVE",
      "name": "Aave",
      "price": 320.7621392318736,
      "rsi": 0.0,
      "volume": 670569106.0028086,
      "percent_change_24h": -5.12791063,
      "buy": 50.01,
      "sell": 49.99,
      "coin_id": {
        "id": 7278,
        "icon_url": "https://s2.coinmarketcap.com/static/img/coins/64x64/7278.png"
      }
    },
    {
      "symbol": "ICP",
      "name": "Internet Computer",
      "price": 10.065332344432454,
      "rsi": 0.0,
      "volume": 174928316.23739707,
      "percent_change_24h": -2.89306235,
      "buy": 50.02,
      "sell": 49.98,
      "coin_id": {
        "id": 8916,
        "icon_url": "https://s2.coinmarketcap.com/static/img/coins/64x64/8916.png"
      }
    },
    {
      "symbol": "POL",
      "name": "POL (ex-MATIC)",
      "price": 0.47676299886615525,
      "rsi": 0.0,
      "volume": 204295569.03249812,
      "percent_change_24h": -1.17756114,
      "buy": 50.02,
      "sell": 49.98,
      "coin_id": {
        "id": 28321,
        "icon_url": "https://s2.coinmarketcap.com/static/img/coins/64x64/28321.png"
      }
    },
    {
      "symbol": "CRO",
      "name": "Cronos",
      "price": 0.14927912104048005,
      "rsi": 0.0,
      "volume": 29501482.66244619,
      "percent_change_24h": -0.98289662,
      "buy": 50.11,
      "sell": 49.89,
      "coin_id": {
        "id": 3635,
        "icon_url": "https://s2.coinmarketcap.com/static/img/coins/64x64/3635.png"
      }
    },
    {
      "symbol": "ETC",
      "name": "Ethereum Classic",
      "price": 25.960337781109452,
      "rsi": 0.0,
      "volume": 208648380.30836773,
      "percent_change_24h": -0.1455237,
      "buy": 50.01,
      "sell": 49.99,
      "coin_id": {
        "id": 1321,
        "icon_url": "https://s2.coinmarketcap.com/static/img/coins/64x64/1321.png"
      }
    },
    {
      "symbol": "VET",
      "name": "VeChain",
      "price": 0.04573890350700247,
      "rsi": 0.0,
      "volume": 79908355.76164332,
      "percent_change_24h": -3.18767321,
      "buy": 50.04,
      "sell": 49.96,
      "coin_id": {
        "id": 3077,
        "icon_url": "https://s2.coinmarketcap.com/static/img/coins/64x64/3077.png"
      }
    },
    {
      "symbol": "RENDER",
      "name": "Render",
      "price": 7.013823791674481,
      "rsi": 0.0,
      "volume": 370313587.0162599,
      "percent_change_24h": -2.672429,
      "buy": 50.01,
      "sell": 49.99,
      "coin_id": {
        "id": 5690,
        "icon_url": "https://s2.coinmarketcap.com/static/img/coins/64x64/5690.png"
      }
    },
    {
      "symbol": "FIL",
      "name": "Filecoin",
      "price": 4.927600025323704,
      "rsi": 0.0,
      "volume": 228511310.23376504,
      "percent_change_24h": -1.60486494,
      "buy": 50.01,
      "sell": 49.99,
      "coin_id": {
        "id": 2280,
        "icon_url": "https://s2.coinmarketcap.com/static/img/coins/64x64/2280.png"
      }
    },
    {
      "symbol": "ALGO",
      "name": "Algorand",
      "price": 0.3301312334468161,
      "rsi": 0.0,
      "volume": 245889010.5336543,
      "percent_change_24h": -6.11225549,
      "buy": 50.02,
      "sell": 49.98,
      "coin_id": {
        "id": 4030,
        "icon_url": "https://s2.coinmarketcap.com/static/img/coins/64x64/4030.png"
      }
    },
    {
      "symbol": "ATOM",
      "name": "Cosmos",
      "price": 6.46426920965254,
      "rsi": 0.0,
      "volume": 154253291.24237087,
      "percent_change_24h": -1.25119555,
      "buy": 50.02,
      "sell": 49.98,
      "coin_id": {
        "id": 30019,
        "icon_url": "https://s2.coinmarketcap.com/static/img/coins/64x64/30019.png"
      }
    }
  ],
  "top_10_cryptos": [
    {
      "rank": 1,
      "name": "Bitcoin",
      "symbol": "BTC",
      "market_cap": 1859061084957.0894,
      "price": 93882.83226547886,
      "volume": 50447076443.69968
    },
    {
      "rank": 2,
      "name": "Ethereum",
      "symbol": "ETH",
      "market_cap": 398145078474.994,
      "price": 3305.0825441958655,
      "volume": 25099100708.39037
    },
    {
      "rank": 3,
      "name": "Tether USDt",
      "symbol": "USDT",
      "market_cap": 139211116057.25333,
      "price": 0.9983543868817362,
      "volume": 107719795722.96152
    },
    {
      "rank": 4,
      "name": "XRP",
      "symbol": "XRP",
      "market_cap": 122620207318.55028,
      "price": 2.1358599964297604,
      "volume": 5680503317.533827
    },
    {
      "rank": 5,
      "name": "BNB",
      "symbol": "BNB",
      "market_cap": 99074319688.10744,
      "price": 687.9812487919849,
      "volume": 1915245436.7426693
    },
    {
      "rank": 6,
      "name": "Solana",
      "symbol": "SOL",
      "market_cap": 88123952260.85913,
      "price": 183.7702748501533,
      "volume": 2867695453.3879113
    },
    {
      "rank": 7,
      "name": "Dogecoin",
      "symbol": "DOGE",
      "market_cap": 45762290630.46249,
      "price": 0.3105125402403852,
      "volume": 2302198806.636281
    },
    {
      "rank": 8,
      "name": "USDC",
      "symbol": "USDC",
      "market_cap": 43514976629.01793,
      "price": 0.999869633245815,
      "volume": 6791761710.4986725
    },
    {
      "rank": 9,
      "name": "Cardano",
      "symbol": "ADA",
      "market_cap": 30485034840.684376,
      "price": 0.8677311009073819,
      "volume": 902925243.903361
    },
    {
      "rank": 10,
      "name": "TRON",
      "symbol": "TRX",
      "market_cap": 22304863981.258537,
      "price": 0.2587455536696148,
      "volume": 1306721757.3933837
    }
  ],
  "best_bet": {
    "symbol": "CRO",
    "name": "Cronos",
    "price": 0.14927912104048005,
    "rsi": 0.0,
    "volume": 29501482.66244619,
    "percent_change_24h": -0.98289662,
    "buy": 50.11,
    "sell": 49.89,
    "coin_id": {
      "id": 3635,
      "icon_url": "https://s2.coinmarketcap.com/static/img/coins/64x64/3635.png"
    }
  },
  "suggested_holding_time": 14,
  "projected_profit_per_100": -12.92,
  "timestamp": "2024-12-27 17:21:11 UTC"
}